MANIFEST.in
README.md
setup.py
bin/cluster_info.sh
bin/kube
bin/kube_bin/dump_cluster.sh
bin/kube_bin/gssh
bin/kube_bin/ii
bin/kube_bin/k
bin/kube_bin/kappconfig
bin/kube_bin/kd
bin/kube_bin/kg
bin/kube_bin/khash
bin/kube_bin/klogs
bin/kube_bin/kp
bin/kube_bin/kresources
bin/kube_bin/kubetail
bin/kube_bin/kusage
indico_install/__init__.py
indico_install/cluster_manager.py
indico_install/config.py
indico_install.egg-info/PKG-INFO
indico_install.egg-info/SOURCES.txt
indico_install.egg-info/dependency_links.txt
indico_install.egg-info/entry_points.txt
indico_install.egg-info/requires.txt
indico_install.egg-info/top_level.txt
indico_install/encoder/__init__.py
indico_install/generate/__init__.py
indico_install/generate/cluster_info.py
indico_install/generate/update.py
indico_install/helm/__init__.py
indico_install/helm/apply.py
indico_install/helm/install.py
indico_install/helm/render.py
indico_install/helm/upload.py
indico_install/infra/__init__.py
indico_install/infra/init.py
indico_install/infra/input_utils.py
indico_install/infra/aks/__init__.py
indico_install/infra/aks/cluster.yaml
indico_install/infra/aks/setup.py
indico_install/infra/aks/cluster/__init__.py
indico_install/infra/aks/storage/__init__.py
indico_install/infra/eks/__init__.py
indico_install/infra/eks/cluster.yaml
indico_install/infra/eks/config.py
indico_install/infra/eks/infra_utils.py
indico_install/infra/eks/cluster/__init__.py
indico_install/infra/eks/database/__init__.py
indico_install/infra/eks/network/__init__.py
indico_install/infra/eks/storage/__init__.py
indico_install/infra/gke/__init__.py
indico_install/infra/gke/cluster.py
indico_install/infra/gke/env_confs.py
indico_install/infra/single_node/__init__.py
indico_install/infra/single_node/cluster.yaml
indico_install/infra/single_node/bin/indico_infra.sh
indico_install/infra/single_node/bin/infra/check_infra.sh
indico_install/infra/single_node/bin/infra/ubuntu_setup.sh
indico_install/infra/single_node/bin/infra/utils.sh
indico_install/inspect/__init__.py
indico_install/kube/__init__.py
indico_install/kube/pod.py
indico_install/kube/svc/__init__.py
indico_install/kube/svc/manage.py
indico_install/kube/svc/restart.py
indico_install/kube/svc/scale.py
