Metadata-Version: 2.1
Name: indico-install
Version: 2.2.0
Summary: An indico install platform
Author: Indico
Author-email: engineering@indico.io
License: UNKNOWN
Platform: UNKNOWN
Provides-Extra: aks
Provides-Extra: eks
Provides-Extra: indico
Provides-Extra: saml
